bns_geometry3d/__init__.py
bns_geometry3d/shapes.py
bns_geometry3d-0.1.0.dist-info/LICENSE
bns_geometry3d-0.1.0.dist-info/METADATA
bns_geometry3d-0.1.0.dist-info/WHEEL
bns_geometry3d-0.1.0.dist-info/top_level.txt
bns_geometry3d-0.1.0.dist-info/RECORD
